databaseops/__init__.py
databaseops/helper/__init__.py
databaseops/helper/_data_type_conversions.py
databaseops/mysql/__init__.py
databaseops/mysql/mysqldatabase.py
databaseops/mysql/mysqlops.py
databaseops/mysql/mysqltable.py
databaseops-1.0.0.dist-info/LICENSE
databaseops-1.0.0.dist-info/METADATA
databaseops-1.0.0.dist-info/WHEEL
databaseops-1.0.0.dist-info/top_level.txt
databaseops-1.0.0.dist-info/RECORD
