Metadata-Version: 2.1
Name: databaseops
Version: 1.0.0
Summary: Work with Database as it is dataframe, No need to remember sql queries
Home-page: https://github.com/AnkushBhise/databaseops/
Author: Ankush Bhise
Author-email: ankushbhise.18@gmail.com
License: MIT
Platform: UNKNOWN
Classifier: License :: OSI Approved :: MIT License
Classifier: Programming Language :: Python :: 3
Requires-Dist: sqlalchemy
Requires-Dist: PyMySQL
Requires-Dist: pandas
